CHANGELOG.txt
LICENSE.txt
MANIFEST.in
README.txt
__init__.py
setup.py
Harsh_Simple_Calculator.egg-info/PKG-INFO
Harsh_Simple_Calculator.egg-info/SOURCES.txt
Harsh_Simple_Calculator.egg-info/dependency_links.txt
Harsh_Simple_Calculator.egg-info/top_level.txt
venv/Lib/site-packages/Pympler-0.9-py3.9.egg-info/SOURCES.txt
venv/Lib/site-packages/Pympler-0.9-py3.9.egg-info/dependency_links.txt
venv/Lib/site-packages/Pympler-0.9-py3.9.egg-info/installed-files.txt
venv/Lib/site-packages/Pympler-0.9-py3.9.egg-info/top_level.txt
venv/Lib/site-packages/_distutils_hack/__init__.py
venv/Lib/site-packages/_distutils_hack/override.py
venv/Lib/site-packages/pip/__init__.py
venv/Lib/site-packages/pip/__main__.py
venv/Lib/site-packages/pip-21.0.1.dist-info/LICENSE.txt
venv/Lib/site-packages/pip-21.0.1.dist-info/entry_points.txt
venv/Lib/site-packages/pip-21.0.1.dist-info/top_level.txt
venv/Lib/site-packages/pip/_internal/__init__.py
venv/Lib/site-packages/pip/_internal/build_env.py
venv/Lib/site-packages/pip/_internal/cache.py
venv/Lib/site-packages/pip/_internal/configuration.py
venv/Lib/site-packages/pip/_internal/exceptions.py
venv/Lib/site-packages/pip/_internal/locations.py
venv/Lib/site-packages/pip/_internal/main.py
venv/Lib/site-packages/pip/_internal/pyproject.py
venv/Lib/site-packages/pip/_internal/self_outdated_check.py
venv/Lib/site-packages/pip/_internal/wheel_builder.py
venv/Lib/site-packages/pip/_internal/cli/__init__.py
venv/Lib/site-packages/pip/_internal/cli/autocompletion.py
venv/Lib/site-packages/pip/_internal/cli/base_command.py
venv/Lib/site-packages/pip/_internal/cli/cmdoptions.py
venv/Lib/site-packages/pip/_internal/cli/command_context.py
venv/Lib/site-packages/pip/_internal/cli/main.py
venv/Lib/site-packages/pip/_internal/cli/main_parser.py
venv/Lib/site-packages/pip/_internal/cli/parser.py
venv/Lib/site-packages/pip/_internal/cli/progress_bars.py
venv/Lib/site-packages/pip/_internal/cli/req_command.py
venv/Lib/site-packages/pip/_internal/cli/spinners.py
venv/Lib/site-packages/pip/_internal/cli/status_codes.py
venv/Lib/site-packages/pip/_internal/commands/__init__.py
venv/Lib/site-packages/pip/_internal/commands/cache.py
venv/Lib/site-packages/pip/_internal/commands/check.py
venv/Lib/site-packages/pip/_internal/commands/completion.py
venv/Lib/site-packages/pip/_internal/commands/configuration.py
venv/Lib/site-packages/pip/_internal/commands/debug.py
venv/Lib/site-packages/pip/_internal/commands/download.py
venv/Lib/site-packages/pip/_internal/commands/freeze.py
venv/Lib/site-packages/pip/_internal/commands/hash.py
venv/Lib/site-packages/pip/_internal/commands/help.py
venv/Lib/site-packages/setuptools-53.0.0.dist-info/dependency_links.txt
venv/Lib/site-packages/setuptools-53.0.0.dist-info/entry_points.txt
venv/Lib/site-packages/setuptools-53.0.0.dist-info/top_level.txt
